aia_utilities/__init__.py
aia_utilities/aia_utilities.py
aia_utilities/dump.rdb
aia_utilities/test.ipynb
aia_utilities-0.1.17.dist-info/licenses/LICENSE
aia_utilities-0.1.17.dist-info/METADATA
aia_utilities-0.1.17.dist-info/WHEEL
aia_utilities-0.1.17.dist-info/top_level.txt
aia_utilities-0.1.17.dist-info/RECORD
