Metadata-Version: 2.4
Name: aia-utilities
Version: 0.1.17
Summary: Small utilities for Redis
Home-page: https://github.com/surgelove/aia_utilities
Author: surgelove
Author-email: 
License: MIT
Classifier: Programming Language :: Python :: 3
Classifier: License :: OSI Approved :: MIT License
Classifier: Operating System :: OS Independent
Requires-Python: >=3.8
License-File: LICENSE
Requires-Dist: redis>=4.0
Dynamic: license-file
